{"status": "success", "totalResults": 7119, "results": [{"article_id": "a4e51f8b7b01a7740e406a6011cb7979", "title": "\u0627\u0654\u0633\u0639\u0627\u0631 \u0627\u0644\u0639\u0645\u0644\u0627\u062a \u0627\u0644\u0639\u0631\u0628\u064a\u0629 \u0648\u0627\u0644\u0627\u0654\u062c\u0646\u0628\u064a\u0629 \u0627\u0654\u0645\u0627\u0645 \u0627\u0644\u062c\u0646\u064a\u0647 \u0627\u0644\u0645\u0635\u0631\u064a \u0641\u064a \u0645\u0635\u0631 \u0627\u0644\u064a\u0648\u0645 \u0627\u0644\u0627\u0654\u0631\u0628\u0639\u0627\u0621 22 \u064a\u0646\u0627\u064a\u0631 / \u0643\u0627\u0646\u0648\u0646 \u0627\u0644\u062b\u0627\u0646\u064a 2025", "link": "https://www.egypt-today.com/87/015424-%D8%A3%D8%B3%D8%B9%D8%A7%D8%B1-%D8%A7%D9%84%D8%B9%D9%85%D9%84%D8%A7%D8%AA-%D8%A7%D9%84%D8%B9%D8%B1%D8%A8%D9%8A%D8%A9-%D9%88%D8%A7%D9%84%D8%A3%D8%AC%D9%86%D8%A8%D9%8A%D8%A9-%D8%A3%D9%85%D8%A7%D9%85-%D8%A7%D9%84%D8%AC%D9%86%D9%8A%D9%87-%D8%A7%D9%84%D9%85%D8%B5%D8%B1%D9%8A-%D9%81%D9%8A-%D9%85%D8%B5%D8%B1-%D8%A7%D9%84%D9%8A%D9%88%D9%85-%D8%A7%D9%84%D8%A3%D8%B1%D8%A8%D8%B9%D8%A7%D8%A1-22", "keywords": null, "creator": null, "video_url": null, "description": "\u062a\u0632\u0627\u064a\u062f\u062a \u0645\u0639\u062f\u0644\u0627\u062a \u0628\u062d\u062b \u0639\u062f\u062f \u0643\u0628\u064a\u0631 \u0645\u0646 \u0627\u0644\u0645\u0648\u0627\u0637\u0646\u064a\u0646 \u0639\u0628\u0631 \u0645\u062d\u0631\u0643 \u0627\u0644\u0628\u062d\u062b \u00ab\u062c\u0648\u062c\u0644\u00bb \u0639\u0646 \u0633\u0639\u0631 \u0627\u0644\u062f\u0648\u0644\u0627\u0631 \u0627\u0644\u0627\u0653\u0646 \u0648\u0627\u0644\u0639\u0645\u0644\u0627\u062a \u0627\u0644\u0639\u0631\u0628\u064a\u0629 \u0648\u0627\u0644\u0627\u0654\u062c\u0646\u0628\u064a\u0629\u060c \u0645\u0642\u0627\u0628\u0644 \u0627\u0644\u062c\u0646\u064a\u0647 \u0627\u0644\u0645\u0635\u0631\u064a\u060c \u0627\u0644\u064a\u0648\u0645 \u0648\u0641\u064a\u0645\u0627 \u064a\u0644\u064a \u0627\u0653\u062e\u0631 \u062a\u062d\u062f\u064a\u062b \u0644\u0640 \u0627\u0654\u0633\u0639\u0627\u0631 \u0627\u0644\u062f\u0648\u0644\u0627\u0631 \u0648", "content": "ONLY AVAILABLE IN PAID PLANS", "pubDate": "2025-01-22 02:27:11", "pubDateTZ": "UTC", "image_url": "https://img.egypt-today.com/2021/08/normal/dollar.jpg", "source_id": "egypt_today", "source_priority": 535683, "source_name": "Egypt Today", "source_url": "https://www.egypt-today.com", "source_icon": null, "language": "arabic", "country": ["egypt"], "category": ["business"], "ai_tag": "ONLY AVAILABLE IN PROFESSIONAL AND CORPORATE PLANS", "sentiment": "ONLY AVAILABLE IN PROFESSIONAL AND CORPORATE PLANS", "sentiment_stats": "ONLY AVAILABLE IN PROFESSIONAL AND CORPORATE PLANS", "ai_region": "ONLY AVAILABLE IN CORPORATE PLANS", "ai_org": "ONLY AVAILABLE IN CORPORATE PLANS", "duplicate": false}, {"article_id": "426bbd16d570a5c914239c3be14b949d", "title": "\u0633\u0639\u0631 \u0627\u0644\u064a\u0648\u0631\u0648 \u0627\u0654\u0645\u0627\u0645 \u0627\u0644\u062c\u0646\u064a\u0647 \u0627\u0644\u0645\u0635\u0631\u064a \u0641\u064a \u0645\u0635\u0631 \u0627\u0644\u064a\u0648\u0645 \u0627\u0644\u0627\u0654\u0631\u0628\u0639\u0627\u0621 22 \u064a\u0646\u0627\u064a\u0631 / \u0643\u0627\u0646\u0648\u0646 \u0627\u0644\u062b\u0627\u0646\u064a 2025", "link": "https://www.egypt-today.com/87/015621-%D8%B3%D8%B9%D8%B1-%D8%A7%D9%84%D9%8A%D9%88%D8%B1%D9%88-%D8%A3%D9%85%D8%A7%D9%85-%D8%A7%D9%84%D8%AC%D9%86%D9%8A%D9%87-%D8%A7%D9%84%D9%85%D8%B5%D8%B1%D9%8A-%D9%81%D9%8A-%D9%85%D8%B5%D8%B1-%D8%A7%D9%84%D9%8A%D9%88%D9%85-%D8%A7%D9%84%D8%A3%D8%B1%D8%A8%D8%B9%D8%A7%D8%A1-22-%D9%8A%D9%86%D8%A7%D9%8A%D8%B1", "keywords": null, "creator": null, "video_url": null, "description": "\u0634\u0647\u062f \u0633\u0639\u0631 \u0627\u0644\u064a\u0648\u0631\u0648 \u0645\u0642\u0627\u0628\u0644", "content": "ONLY AVAILABLE IN PAID PLANS", "pubDate": "2025-01-22 02:27:10", "pubDateTZ": "UTC", "image_url": "https://img.egypt-today.com/2022/04/normal/uro.jpg", "source_id": "egypt_today", "source_priority": 535683, "source_name": "Egypt Today", "source_url": "https://www.egypt-today.com", "source_icon": null, "language": "arabic", "country": ["egypt"], "category": ["business"], "ai_tag": "ONLY AVAILABLE IN PROFESSIONAL AND CORPORATE PLANS", "sentiment": "ONLY AVAILABLE IN PROFESSIONAL AND CORPORATE PLANS", "sentiment_stats": "ONLY AVAILABLE IN PROFESSIONAL AND CORPORATE PLANS", "ai_region": "ONLY AVAILABLE IN CORPORATE PLANS", "ai_org": "ONLY AVAILABLE IN CORPORATE PLANS", "duplicate": false}, {"article_id": "af007844d5c038f60ef5d5c05fa9a5f5", "title": "\u0633\u0639\u0631 \u0627\u0644\u0627\u0655\u0633\u062a\u0631\u0644\u064a\u0646\u064a \u0627\u0654\u0645\u0627\u0645 \u0627\u0644\u062c\u0646\u064a\u0647 \u0627\u0644\u0645\u0635\u0631\u064a \u0641\u064a \u0645\u0635\u0631 \u0627\u0644\u064a\u0648\u0645 \u0627\u0644\u0627\u0654\u0631\u0628\u0639\u0627\u0621 22 \u064a\u0646\u0627\u064a\u0631 / \u0643\u0627\u0646\u0648\u0646 \u0627\u0644\u062b\u0627\u0646\u064a 2025", "link": "https://www.egypt-today.com/87/015803-%D8%B3%D8%B9%D8%B1-%D8%A7%D9%84%D8%A5%D8%B3%D8%AA%D8%B1%D9%84%D9%8A%D9%86%D9%8A-%D8%A3%D9%85%D8%A7%D9%85-%D8%A7%D9%84%D8%AC%D9%86%D9%8A%D9%87-%D8%A7%D9%84%D9%85%D8%B5%D8%B1%D9%8A-%D9%81%D9%8A-%D9%85%D8%B5%D8%B1-%D8%A7%D9%84%D9%8A%D9%88%D9%85-%D8%A7%D9%84%D8%A3%D8%B1%D8%A8%D8%B9%D8%A7%D8%A1-22-%D9%8A%D9%86%D8%A7%D9%8A%D8%B1", "keywords": null, "creator": null, "video_url": null, "description": "\u0633\u062c\u0644 \u0633\u0639\u0631", "content": "ONLY AVAILABLE IN PAID PLANS", "pubDate": "2025-01-22 02:27:09", "pubDateTZ": "UTC", "image_url": "https://img.egypt-today.com/2022/03/normal/pound.jpg", "source_id": "egypt_today", "source_priority": 535683, "source_name": "Egypt Today", "source_url": "https://www.egypt-today.com", "source_icon": null, "language": "arabic", "country": ["egypt"], "category": ["business"], "ai_tag": "ONLY AVAILABLE IN PROFESSIONAL AND CORPORATE PLANS", "sentiment": "ONLY AVAILABLE IN PROFESSIONAL AND CORPORATE PLANS", "sentiment_stats": "ONLY AVAILABLE IN PROFESSIONAL AND CORPORATE PLANS", "ai_region": "ONLY AVAILABLE IN CORPORATE PLANS", "ai_org": "ONLY AVAILABLE IN CORPORATE PLANS", "duplicate": false}, {"article_id": "17302c4aaca5b1d06ad7634b0838ef9b", "title": "\u0633\u0639\u0631 \u0627\u0644\u064a\u0646 \u0627\u0644\u064a\u0627\u0628\u0627\u0646\u064a \u0627\u0654\u0645\u0627\u0645 \u0627\u0644\u062c\u0646\u064a\u0647 \u0627\u0644\u0645\u0635\u0631\u064a \u0641\u064a \u0645\u0635\u0631 \u0627\u0644\u064a\u0648\u0645 \u0627\u0644\u0627\u0654\u0631\u0628\u0639\u0627\u0621 22 \u064a\u0646\u0627\u064a\u0631 / \u0643\u0627\u0646\u0648\u0646 \u0627\u0644\u062b\u0627\u0646\u064a 2025", "link": "https://www.egypt-today.com/87/020004-%D8%B3%D8%B9%D8%B1-%D8%A7%D9%84%D9%8A%D9%86-%D8%A7%D9%84%D9%8A%D8%A7%D8%A8%D8%A7%D9%86%D9%8A-%D8%A3%D9%85%D8%A7%D9%85-%D8%A7%D9%84%D8%AC%D9%86%D9%8A%D9%87-%D8%A7%D9%84%D9%85%D8%B5%D8%B1%D9%8A-%D9%81%D9%8A-%D9%85%D8%B5%D8%B1-%D8%A7%D9%84%D9%8A%D9%88%D9%85-%D8%A7%D9%84%D8%A3%D8%B1%D8%A8%D8%B9%D8%A7%D8%A1-22-%D9%8A%D9%86%D8%A7%D9%8A%D8%B1", "keywords": null, "creator": null, "video_url": null, "description": "\u0633\u0639\u0631 \u0627\u0644\u062c\u0646\u064a\u0647 \u0627\u0644\u0645\u0635\u0631\u064a \u0645\u0642\u0627\u0628\u0644", "content": "ONLY AVAILABLE IN PAID PLANS", "pubDate": "2025-01-22 02:27:09", "pubDateTZ": "UTC", "image_url": "https://img.egypt-today.com/2022/03/normal/pound.jpg", "source_id": "egypt_today", "source_priority": 535683, "source_name": "Egypt Today", "source_url": "https://www.egypt-today.com", "source_icon": null, "language": "arabic", "country": ["egypt"], "category": ["business"], "ai_tag": "ONLY AVAILABLE IN PROFESSIONAL AND CORPORATE PLANS", "sentiment": "ONLY AVAILABLE IN PROFESSIONAL AND CORPORATE PLANS", "sentiment_stats": "ONLY AVAILABLE IN PROFESSIONAL AND CORPORATE PLANS", "ai_region": "ONLY AVAILABLE IN CORPORATE PLANS", "ai_org": "ONLY AVAILABLE IN CORPORATE PLANS", "duplicate": false}, {"article_id": "89ab7735c2a6e272fb43a564cde49fe0", "title": "\u0633\u0639\u0631\u064f \u0627\u0644\u062f\u0648\u0644\u0627\u0631\u0650 \u0627\u0644\u0627\u0654\u0645\u064a\u0631\u0643\u064a\u0650 \u0627\u0654\u0645\u0627\u0645 \u0627\u0644\u062c\u0646\u064a\u0647 \u0627\u0644\u0645\u0635\u0631\u064a \u0641\u064a \u0645\u0635\u0631 \u0627\u0644\u064a\u0648\u0645 \u0627\u0644\u0627\u0654\u0631\u0628\u0639\u0627\u0621 22 \u064a\u0646\u0627\u064a\u0631 / \u0643\u0627\u0646\u0648\u0646 \u0627\u0644\u062b\u0627\u0646\u064a 2025", "link": "https://www.egypt-today.com/87/020155-%D8%B3%D8%B9%D8%B1%D9%8F-%D8%A7%D9%84%D8%AF%D9%88%D9%84%D8%A7%D8%B1%D9%90-%D8%A7%D9%84%D8%A3%D9%85%D9%8A%D8%B1%D9%83%D9%8A%D9%90-%D8%A3%D9%85%D8%A7%D9%85-%D8%A7%D9%84%D8%AC%D9%86%D9%8A%D9%87-%D8%A7%D9%84%D9%85%D8%B5%D8%B1%D9%8A-%D9%81%D9%8A-%D9%85%D8%B5%D8%B1-%D8%A7%D9%84%D9%8A%D9%88%D9%85-%D8%A7%D9%84%D8%A3%D8%B1%D8%A8%D8%B9%D8%A7%D8%A1-22-%D9%8A%D9%86%D8%A7%D9%8A%D8%B1", "keywords": null, "creator": null, "video_url": null, "description": "\u0633\u062c\u0644", "content": "ONLY AVAILABLE IN PAID PLANS", "pubDate": "2025-01-22 02:27:08", "pubDateTZ": "UTC", "image_url": "https://img.egypt-today.com/2021/05/normal/dollar2.jpg", "source_id": "egypt_today", "source_priority": 535683, "source_name": "Egypt Today", "source_url": "https://www.egypt-today.com", "source_icon": null, "language": "arabic", "country": ["egypt"], "category": ["business"], "ai_tag": "ONLY AVAILABLE IN PROFESSIONAL AND CORPORATE PLANS", "sentiment": "ONLY AVAILABLE IN PROFESSIONAL AND CORPORATE PLANS", "sentiment_stats": "ONLY AVAILABLE IN PROFESSIONAL AND CORPORATE PLANS", "ai_region": "ONLY AVAILABLE IN CORPORATE PLANS", "ai_org": "ONLY AVAILABLE IN CORPORATE PLANS", "duplicate": false}, {"article_id": "b8e321267ed0c16437c34894ed2c7c95", "title": "\u0633\u0639\u0631 \u0627\u0644\u062c\u0646\u064a\u0647 \u0627\u0644\u0645\u0635\u0631\u064a \u0645\u0642\u0627\u0628\u0644 \u0627\u0644\u0644\u064a\u0631\u0629 \u0627\u0644\u062a\u0631\u0643\u064a\u0629 \u0641\u064a \u0645\u0635\u0631 \u0627\u0644\u064a\u0648\u0645 \u0627\u0644\u0627\u0654\u0631\u0628\u0639\u0627\u0621 22 \u064a\u0646\u0627\u064a\u0631 / \u0643\u0627\u0646\u0648\u0646 \u0627\u0644\u062b\u0627\u0646\u064a 2025", "link": "https://www.egypt-today.com/87/020346-%D8%B3%D8%B9%D8%B1-%D8%A7%D9%84%D8%AC%D9%86%D9%8A%D9%87-%D8%A7%D9%84%D9%85%D8%B5%D8%B1%D9%8A-%D9%85%D9%82%D8%A7%D8%A8%D9%84-%D8%A7%D9%84%D9%84%D9%8A%D8%B1%D8%A9-%D8%A7%D9%84%D8%AA%D8%B1%D9%83%D9%8A%D8%A9-%D9%81%D9%8A-%D9%85%D8%B5%D8%B1-%D8%A7%D9%84%D9%8A%D9%88%D9%85-%D8%A7%D9%84%D8%A3%D8%B1%D8%A8%D8%B9%D8%A7%D8%A1-22-%D9%8A%D9%86%D8%A7%D9%8A%D8%B1", "keywords": null, "creator": null, "video_url": null, "description": "\u0633\u0639\u0631 \u0627\u0644\u062c\u0646\u064a\u0647 \u0627\u0644\u0645\u0635\u0631\u064a \u0645\u0642\u0627\u0628\u0644", "content": "ONLY AVAILABLE IN PAID PLANS", "pubDate": "2025-01-22 02:27:08", "pubDateTZ": "UTC", "image_url": "https://img.egypt-today.com/2021/12/normal/lyra.jpg", "source_id": "egypt_today", "source_priority": 535683, "source_name": "Egypt Today", "source_url": "https://www.egypt-today.com", "source_icon": null, "language": "arabic", "country": ["egypt"], "category": ["business"], "ai_tag": "ONLY AVAILABLE IN PROFESSIONAL AND CORPORATE PLANS", "sentiment": "ONLY AVAILABLE IN PROFESSIONAL AND CORPORATE PLANS", "sentiment_stats": "ONLY AVAILABLE IN PROFESSIONAL AND CORPORATE PLANS", "ai_region": "ONLY AVAILABLE IN CORPORATE PLANS", "ai_org": "ONLY AVAILABLE IN CORPORATE PLANS", "duplicate": false}, {"article_id": "fde4e929124ec3f12a1b6356f0f14302", "title": "\u0633\u0639\u0631 \u0627\u0644\u062c\u0646\u064a\u0629 \u0627\u0644\u0645\u0635\u0631\u064a \u0645\u0642\u0627\u0628\u0644 \u0627\u0644\u0631\u064a\u0627\u0644 \u0642\u0637\u0631\u064a \u0641\u064a \u0645\u0635\u0631 \u0627\u0644\u064a\u0648\u0645 \u0627\u0644\u0627\u0654\u0631\u0628\u0639\u0627\u0621 22 \u064a\u0646\u0627\u064a\u0631 / \u0643\u0627\u0646\u0648\u0646 \u0627\u0644\u062b\u0627\u0646\u064a 2025", "link": "https://www.egypt-today.com/87/020535-%D8%B3%D8%B9%D8%B1-%D8%A7%D9%84%D8%AC%D9%86%D9%8A%D8%A9-%D8%A7%D9%84%D9%85%D8%B5%D8%B1%D9%8A-%D9%85%D9%82%D8%A7%D8%A8%D9%84-%D8%A7%D9%84%D8%B1%D9%8A%D8%A7%D9%84-%D9%82%D8%B7%D8%B1%D9%8A-%D9%81%D9%8A-%D9%85%D8%B5%D8%B1-%D8%A7%D9%84%D9%8A%D9%88%D9%85-%D8%A7%D9%84%D8%A3%D8%B1%D8%A8%D8%B9%D8%A7%D8%A1-22-%D9%8A%D9%86%D8%A7%D9%8A%D8%B1", "keywords": null, "creator": null, "video_url": null, "description": "\u0633\u0639\u0631", "content": "ONLY AVAILABLE IN PAID PLANS", "pubDate": "2025-01-22 02:27:05", "pubDateTZ": "UTC", "image_url": "https://img.egypt-today.com/2022/03/normal/pound.jpg", "source_id": "egypt_today", "source_priority": 535683, "source_name": "Egypt Today", "source_url": "https://www.egypt-today.com", "source_icon": null, "language": "arabic", "country": ["egypt"], "category": ["business"], "ai_tag": "ONLY AVAILABLE IN PROFESSIONAL AND CORPORATE PLANS", "sentiment": "ONLY AVAILABLE IN PROFESSIONAL AND CORPORATE PLANS", "sentiment_stats": "ONLY AVAILABLE IN PROFESSIONAL AND CORPORATE PLANS", "ai_region": "ONLY AVAILABLE IN CORPORATE PLANS", "ai_org": "ONLY AVAILABLE IN CORPORATE PLANS", "duplicate": false}, {"article_id": "54fb3526b5f401505dc54ad36ad0f1e0", "title": "\u0633\u0639\u0631 \u0627\u0644\u062c\u0646\u064a\u0629 \u0627\u0644\u0645\u0635\u0631\u064a \u0645\u0642\u0627\u0628\u0644 \u0627\u0644\u062f\u064a\u0646\u0627\u0631 \u0627\u0644\u0643\u0648\u064a\u062a\u064a \u0641\u064a \u0645\u0635\u0631 \u0627\u0644\u064a\u0648\u0645 \u0627\u0644\u0627\u0654\u0631\u0628\u0639\u0627\u0621 22 \u064a\u0646\u0627\u064a\u0631 / \u0643\u0627\u0646\u0648\u0646 \u0627\u0644\u062b\u0627\u0646\u064a 2025", "link": "https://www.egypt-today.com/87/020734-%D8%B3%D8%B9%D8%B1-%D8%A7%D9%84%D8%AC%D9%86%D9%8A%D8%A9-%D8%A7%D9%84%D9%85%D8%B5%D8%B1%D9%8A-%D9%85%D9%82%D8%A7%D8%A8%D9%84-%D8%A7%D9%84%D8%AF%D9%8A%D9%86%D8%A7%D8%B1-%D8%A7%D9%84%D9%83%D9%88%D9%8A%D8%AA%D9%8A-%D9%81%D9%8A-%D9%85%D8%B5%D8%B1-%D8%A7%D9%84%D9%8A%D9%88%D9%85-%D8%A7%D9%84%D8%A3%D8%B1%D8%A8%D8%B9%D8%A7%D8%A1-22-%D9%8A%D9%86%D8%A7%D9%8A%D8%B1", "keywords": null, "creator": null, "video_url": null, "description": "\u0633\u0639\u0631 \u0627\u0644\u062c\u0646\u064a\u0647 \u0627\u0644\u0645\u0635\u0631\u064a \u0645\u0642\u0627\u0628\u0644", "content": "ONLY AVAILABLE IN PAID PLANS", "pubDate": "2025-01-22 02:27:04", "pubDateTZ": "UTC", "image_url": "https://img.egypt-today.com/2022/03/normal/pound.jpg", "source_id": "egypt_today", "source_priority": 535683, "source_name": "Egypt Today", "source_url": "https://www.egypt-today.com", "source_icon": null, "language": "arabic", "country": ["egypt"], "category": ["business"], "ai_tag": "ONLY AVAILABLE IN PROFESSIONAL AND CORPORATE PLANS", "sentiment": "ONLY AVAILABLE IN PROFESSIONAL AND CORPORATE PLANS", "sentiment_stats": "ONLY AVAILABLE IN PROFESSIONAL AND CORPORATE PLANS", "ai_region": "ONLY AVAILABLE IN CORPORATE PLANS", "ai_org": "ONLY AVAILABLE IN CORPORATE PLANS", "duplicate": false}, {"article_id": "65965ad871255e475655afb233489480", "title": "\u0633\u0639\u0631 \u0627\u0644\u062c\u0646\u064a\u0629 \u0627\u0644\u0645\u0635\u0631\u064a \u0645\u0642\u0627\u0628\u0644 \u0627\u0644\u062f\u0631\u0647\u0645 \u0627\u0644\u0627\u0655\u0645\u0627\u0631\u0627\u062a\u064a \u0641\u064a \u0645\u0635\u0631 \u0627\u0644\u064a\u0648\u0645 \u0627\u0644\u0627\u0654\u0631\u0628\u0639\u0627\u0621 22 \u064a\u0646\u0627\u064a\u0631 / \u0643\u0627\u0646\u0648\u0646 \u0627\u0644\u062b\u0627\u0646\u064a 2025", "link": "https://www.egypt-today.com/87/020942-%D8%B3%D8%B9%D8%B1-%D8%A7%D9%84%D8%AC%D9%86%D9%8A%D8%A9-%D8%A7%D9%84%D9%85%D8%B5%D8%B1%D9%8A-%D9%85%D9%82%D8%A7%D8%A8%D9%84-%D8%A7%D9%84%D8%AF%D8%B1%D9%87%D9%85-%D8%A7%D9%84%D8%A5%D9%85%D8%A7%D8%B1%D8%A7%D8%AA%D9%8A-%D9%81%D9%8A-%D9%85%D8%B5%D8%B1-%D8%A7%D9%84%D9%8A%D9%88%D9%85-%D8%A7%D9%84%D8%A3%D8%B1%D8%A8%D8%B9%D8%A7%D8%A1-22-%D9%8A%D9%86%D8%A7%D9%8A%D8%B1", "keywords": null, "creator": null, "video_url": null, "description": "\u0633\u0639\u0631 \u0627\u0644\u062c\u0646\u064a\u0647 \u0627\u0644\u0645\u0635\u0631\u064a \u0645\u0642\u0627\u0628\u0644", "content": "ONLY AVAILABLE IN PAID PLANS", "pubDate": "2025-01-22 02:27:04", "pubDateTZ": "UTC", "image_url": "https://img.egypt-today.com/2022/03/normal/pound.jpg", "source_id": "egypt_today", "source_priority": 535683, "source_name": "Egypt Today", "source_url": "https://www.egypt-today.com", "source_icon": null, "language": "arabic", "country": ["egypt"], "category": ["business"], "ai_tag": "ONLY AVAILABLE IN PROFESSIONAL AND CORPORATE PLANS", "sentiment": "ONLY AVAILABLE IN PROFESSIONAL AND CORPORATE PLANS", "sentiment_stats": "ONLY AVAILABLE IN PROFESSIONAL AND CORPORATE PLANS", "ai_region": "ONLY AVAILABLE IN CORPORATE PLANS", "ai_org": "ONLY AVAILABLE IN CORPORATE PLANS", "duplicate": false}, {"article_id": "32c735cfe0f8126e9adf0729ebec89b2", "title": "\u0633\u0639\u0631 \u0627\u0644\u0631\u064a\u0627\u0644 \u0627\u0644\u0633\u0639\u0648\u062f\u064a \u062f\u0627\u062e\u0644 \u0627\u0644\u0628\u0646\u0648\u0643 \u0627\u0644\u0645\u0635\u0631\u064a\u0629 \u0627\u0644\u064a\u0648\u0645 \u0627\u0644\u0627\u0654\u0631\u0628\u0639\u0627\u0621 22 \u064a\u0646\u0627\u064a\u0631 / \u0643\u0627\u0646\u0648\u0646 \u0627\u0644\u062b\u0627\u0646\u064a 2025", "link": "https://www.egypt-today.com/87/021135-%D8%B3%D8%B9%D8%B1-%D8%A7%D9%84%D8%B1%D9%8A%D8%A7%D9%84-%D8%A7%D9%84%D8%B3%D8%B9%D9%88%D8%AF%D9%8A-%D8%AF%D8%A7%D8%AE%D9%84-%D8%A7%D9%84%D8%A8%D9%86%D9%88%D9%83-%D8%A7%D9%84%D9%85%D8%B5%D8%B1%D9%8A%D8%A9-%D8%A7%D9%84%D9%8A%D9%88%D9%85-%D8%A7%D9%84%D8%A3%D8%B1%D8%A8%D8%B9%D8%A7%D8%A1-22-%D9%8A%D9%86%D8%A7%D9%8A%D8%B1-%D9%83%D8%A7%D9%86%D9%88%D9%86", "keywords": null, "creator": null, "video_url": null, "description": "\u0634\u0647\u062f \u0633\u0639\u0631 \u0627\u0644\u0631\u064a\u0627\u0644 \u0627\u0644\u0633\u0639\u0648\u062f\u064a \u0645\u0642\u0627\u0628\u0644", "content": "ONLY AVAILABLE IN PAID PLANS", "pubDate": "2025-01-22 02:27:02", "pubDateTZ": "UTC", "image_url": "https://img.egypt-today.com/2021/08/normal/centrel-bank.jpg", "source_id": "egypt_today", "source_priority": 535683, "source_name": "Egypt Today", "source_url": "https://www.egypt-today.com", "source_icon": null, "language": "arabic", "country": ["egypt"], "category": ["business"], "ai_tag": "ONLY AVAILABLE IN PROFESSIONAL AND CORPORATE PLANS", "sentiment": "ONLY AVAILABLE IN PROFESSIONAL AND CORPORATE PLANS", "sentiment_stats": "ONLY AVAILABLE IN PROFESSIONAL AND CORPORATE PLANS", "ai_region": "ONLY AVAILABLE IN CORPORATE PLANS", "ai_org": "ONLY AVAILABLE IN CORPORATE PLANS", "duplicate": false}], "nextPage": "1737512822593404736"}