{"status": "success", "totalResults": 9519, "results": [{"article_id": "adfe25d9993b5181e3bda36b9257fc7c", "link": "https://www.vetogate.com/5683021", "title": "\u0627\u0654\u0647\u062f\u0627\u0641 \u0645\u0628\u0627\u0631\u0627\u0629 \u0627\u0644\u0643\u0648\u0646\u063a\u0648 \u0627\u0644\u062f\u064a\u0645\u0642\u0631\u0627\u0637\u064a\u0629 \u0648\u0627\u0654\u0648\u0632\u0628\u0643\u0633\u062a\u0627\u0646 \u0641\u064a \u0643\u0627\u0654\u0633 \u0627\u0644\u0639\u0627\u0644\u0645 2026 (\u0641\u064a\u062f\u064a\u0648)", "description": "\u0643\u0627\u0654\u0633 \u0627\u0644\u0639\u0627\u0644\u0645 2026\u060c \u0642\u0644\u0628 \u0627\u0644\u0643\u0648\u0646\u063a\u0648 \u0627\u0644\u062f\u064a\u0645\u0642\u0631\u0627\u0637\u064a\u0629 \u062a\u0627\u0654\u062e\u0631\u0647 \u0627\u0654\u0645\u0627\u0645 \u0627\u0654\u0648\u0632\u0628\u0643\u0633\u062a\u0627\u0646 \u0628\u0647\u062f\u0641 \u0644\u0644\u0641\u0648\u0632 \u0628\u0646\u062a\u064a\u062c\u0629 3-1 \u0641\u064a \u0627\u0644\u0645\u0628\u0627\u0631\u0627\u0629 \u0627\u0644\u062a\u064a \u062c\u0631\u062a \u0628\u064a\u0646\u0647\u0645\u0627 \u0636\u0645\u0646 \u0627\u0644\u062c\u0648\u0644\u0629 \u0627\u0644\u062b\u0627\u0644\u062b\u0629 \u0648\u0627\u0644\u0627\u0654\u062e\u064a\u0631\u0629", "content": "ONLY AVAILABLE IN PAID PLANS", "keywords": null, "creator": ["\u0641\u064a\u062a\u0648"], "language": "arabic", "country": ["egypt"], "category": ["top", "sports"], "datatype": "news", "pubDate": "2026-06-28 02:10:22", "pubDateTZ": "UTC", "fetched_at": "2026-06-28 02:10:22", "image_url": "https://www.vetogate.com/UploadCache/libfiles/587/5/600x338o/694.jpg", "video_url": null, "source_id": "vetogate", "source_name": "\u0641\u064a\u062a\u0648", "source_priority": 59162, "source_url": "https://www.vetogate.com", "source_icon": "https://n.bytvi.com/vetogate.png", "sentiment": "ONLY AVAILABLE IN PROFESSIONAL AND CORPORATE PLANS", "sentiment_stats": "ONLY AVAILABLE IN PROFESSIONAL AND CORPORATE PLANS", "ai_tag": "ONLY AVAILABLE IN PROFESSIONAL AND CORPORATE PLANS", "ai_region": "ONLY AVAILABLE IN CORPORATE PLANS", "ai_org": "ONLY AVAILABLE IN CORPORATE PLANS", "ai_summary": "ONLY AVAILABLE IN PAID PLANS", "duplicate": false}, {"article_id": "7620bad880086731216b624c16673298", "link": "https://www.vetogate.com/5683015", "title": "\u0631\u0648\u0646\u0627\u0644\u062f\u0648 \u064a\u0637\u0627\u0631\u062f \u0645\u064a\u0633\u064a\u060c \u0627\u0654\u0643\u062b\u0631 \u0627\u0644\u0644\u0627\u0639\u0628\u064a\u0646 \u062e\u0648\u0636\u0627 \u0644\u0644\u0645\u0628\u0627\u0631\u064a\u0627\u062a \u0641\u064a \u0643\u0627\u0654\u0633 \u0627\u0644\u0639\u0627\u0644\u0645", "description": "\u0643\u0627\u0654\u0633 \u0627\u0644\u0639\u0627\u0644\u0645\u060c \u0648\u0627\u0635\u0644 \u0643\u0631\u064a\u0633\u062a\u064a\u0627\u0646\u0648 \u0631\u0648\u0646\u0627\u0644\u062f\u0648 \u0645\u0644\u0627\u062d\u0642\u0629 \u0627\u0644\u0631\u0642\u0645 \u0627\u0644\u062a\u0627\u0631\u064a\u062e\u064a \u0627\u0644\u0630\u064a \u064a\u062d\u0645\u0644\u0647 \u0644\u064a\u0648\u0646\u064a\u0644 \u0645\u064a\u0633\u064a \u0641\u064a \u0642\u0627\u064a\u0654\u0645\u0629 \u0627\u0654\u0643\u062b\u0631 \u0627\u0644\u0644\u0627\u0639\u0628\u064a\u0646 \u062e\u0648\u0636\u064b\u0627 \u0644\u0644\u0645\u0628\u0627\u0631\u064a\u0627\u062a \u0641\u064a \u062a\u0627\u0631\u064a\u062e \u0643\u0627\u0654\u0633 \u0627\u0644\u0639\u0627\u0644\u0645.", "content": "ONLY AVAILABLE IN PAID PLANS", "keywords": null, "creator": ["\u0641\u064a\u062a\u0648"], "language": "arabic", "country": ["egypt"], "category": ["top", "sports"], "datatype": "news", "pubDate": "2026-06-28 02:10:04", "pubDateTZ": "UTC", "fetched_at": "2026-06-28 02:10:04", "image_url": "https://www.vetogate.com/UploadCache/libfiles/527/6/600x338o/555.jpg", "video_url": null, "source_id": "vetogate", "source_name": "\u0641\u064a\u062a\u0648", "source_priority": 59162, "source_url": "https://www.vetogate.com", "source_icon": "https://n.bytvi.com/vetogate.png", "sentiment": "ONLY AVAILABLE IN PROFESSIONAL AND CORPORATE PLANS", "sentiment_stats": "ONLY AVAILABLE IN PROFESSIONAL AND CORPORATE PLANS", "ai_tag": "ONLY AVAILABLE IN PROFESSIONAL AND CORPORATE PLANS", "ai_region": "ONLY AVAILABLE IN CORPORATE PLANS", "ai_org": "ONLY AVAILABLE IN CORPORATE PLANS", "ai_summary": "ONLY AVAILABLE IN PAID PLANS", "duplicate": false}, {"article_id": "40f9264d5a872931f631a06ff18a99c5", "link": "https://menafn.com/1111321996/Netanyahu-Vows-to-Hold-Strategic-Shqif-Area-Despite-Lebanon-Pullback", "title": "Netanyahu Vows to Hold Strategic Shqif Area Despite Lebanon Pullback", "description": "(MENAFN) Prime Minister Benjamin Netanyahu said Saturday that Israeli forces would begin pulling back from two \"pilot areas\" in southern Lebanon while keeping troops entrenched in the strategically ...", "content": "ONLY AVAILABLE IN PAID PLANS", "keywords": null, "creator": null, "language": "english", "country": ["qatar", "kuwait", "yemen", "egypt", "syria", "lebanon", "morocco", "libya", "bahrain", "united arab emirates", "algeria", "tunisia", "iraq", "saudi arabia", "jordan"], "category": ["top", "politics"], "datatype": "news", "pubDate": "2026-06-28 02:09:57", "pubDateTZ": "UTC", "fetched_at": "2026-06-28 07:35:33", "image_url": null, "video_url": null, "source_id": "menafn", "source_name": "Menafn", "source_priority": 28392, "source_url": "https://menafn.com", "source_icon": "https://n.bytvi.com/menafn.png", "sentiment": "ONLY AVAILABLE IN PROFESSIONAL AND CORPORATE PLANS", "sentiment_stats": "ONLY AVAILABLE IN PROFESSIONAL AND CORPORATE PLANS", "ai_tag": "ONLY AVAILABLE IN PROFESSIONAL AND CORPORATE PLANS", "ai_region": "ONLY AVAILABLE IN CORPORATE PLANS", "ai_org": "ONLY AVAILABLE IN CORPORATE PLANS", "ai_summary": "ONLY AVAILABLE IN PAID PLANS", "duplicate": false}, {"article_id": "381066da82c450f972406c65771583a6", "link": "https://www.vetogate.com/5679273", "title": "\u0645\u0648\u0627\u0642\u064a\u062a \u0627\u0644\u0635\u0644\u0627\u0629 \u0627\u0644\u064a\u0648\u0645 \u0627\u0644\u0627\u0654\u062d\u062f 28 - 6 - 2026 \u0641\u064a \u0627\u0644\u0642\u0627\u0647\u0631\u0629 \u0648\u0627\u0644\u0645\u062d\u0627\u0641\u0638\u0627\u062a", "description": "\u0645\u0648\u0627\u0642\u064a\u062a \u0627\u0644\u0635\u0644\u0627\u0629 \u0627\u0644\u064a\u0648\u0645 \u060c \u0639\u0646 \u0627\u0654\u0628\u064a \u0645\u0648\u0633\u0649 \u0627\u0644\u0627\u0654\u0634\u0639\u0631\u0649 \u0631\u0636\u0649 \u0627\u0644\u0644\u0647 \u0639\u0646\u0647 \u0642\u0627\u0644: \u0642\u0627\u0644 \u0627\u0644\u0646\u0628\u064a \u0635\u0644\u0649 \u0627\u0644\u0644\u0647 \u0639\u0644\u064a\u0647 \u0648\u0633\u0644\u0645: \" \u0627\u0654\u0639\u0638\u0645 \u0627\u0644\u0646\u0627\u0633 \u0627\u0654\u062c\u0631\u0627 \u0641\u064a \u0627\u0644\u0635\u0644\u0627\u0629 \u0627\u0654\u0628\u0639\u062f\u0647\u0645\u060c \u0641\u0627\u0654\u0628\u0639\u062f\u0647\u0645 \u0645\u0645\u0634\u0649 \u0648\u0627\u0644\u0630\u064a \u064a\u0646\u062a\u0638\u0631 \u0627\u0644\u0635\u0644\u0627\u0629 \u062d\u062a\u0649 \u064a\u0635\u0644\u064a\u0647\u0627 \u0645\u0639 \u0627\u0644\u0627\u0655\u0645\u0627\u0645 \u0627\u0654\u0639\u0638\u0645 \u0627\u0654\u062c\u0631\u0627 \u0645\u0646 \u0627\u0644\u0630\u064a \u064a\u0635\u0644\u064a\u060c \u062b\u0645 \u064a\u0646\u0627\u0645 \" \u0648\u0639\u0646 \u0627\u0654\u0628\u064a \u0647\u0631\u064a\u0631\u0629 \u0631\u0636\u0649 \u0627\u0644\u0644\u0647 \u0639\u0646\u0647 \u0642\u0627\u0644: \u0642\u0627\u0644 \u0631\u0633\u0648\u0644 \u0627\u0644\u0644\u0647 \u0635\u0644\u0649 \u0627\u0644\u0644\u0647 \u0639\u0644\u064a\u0647 \u0648\u0633\u0644\u0645: \" \u0645\u0646 \u062a\u0637\u0647\u0631 \u0641\u064a \u0628\u064a\u062a\u0647\u060c \u062b\u0645", "content": "ONLY AVAILABLE IN PAID PLANS", "keywords": null, "creator": ["\u0641\u064a\u062a\u0648"], "language": "arabic", "country": ["egypt"], "category": ["top", "lifestyle", "politics"], "datatype": "news", "pubDate": "2026-06-28 02:09:46", "pubDateTZ": "UTC", "fetched_at": "2026-06-28 02:09:46", "image_url": "https://www.vetogate.com/UploadCache/libfiles/587/0/600x338o/418.jpg", "video_url": null, "source_id": "vetogate", "source_name": "\u0641\u064a\u062a\u0648", "source_priority": 59162, "source_url": "https://www.vetogate.com", "source_icon": "https://n.bytvi.com/vetogate.png", "sentiment": "ONLY AVAILABLE IN PROFESSIONAL AND CORPORATE PLANS", "sentiment_stats": "ONLY AVAILABLE IN PROFESSIONAL AND CORPORATE PLANS", "ai_tag": "ONLY AVAILABLE IN PROFESSIONAL AND CORPORATE PLANS", "ai_region": "ONLY AVAILABLE IN CORPORATE PLANS", "ai_org": "ONLY AVAILABLE IN CORPORATE PLANS", "ai_summary": "ONLY AVAILABLE IN PAID PLANS", "duplicate": false}, {"article_id": "01e71a989c91a6834e6347998e38fa59", "link": "https://www.vetogate.com/5683020", "title": "\u0632\u0644\u0632\u0627\u0644 \u062c\u062f\u064a\u062f \u064a\u0636\u0631\u0628 \u0641\u0646\u0632\u0648\u064a\u0644\u0627 \u0648\u0627\u0631\u062a\u0641\u0627\u0639 \u0639\u062f\u062f \u0636\u062d\u0627\u064a\u0627 \u0627\u0644\u0632\u0644\u0632\u0627\u0644\u064a\u0646 \u0627\u0655\u0644\u0649 1430 \u0642\u062a\u064a\u0644\u0627 \u0648\u0627\u0653\u0644\u0627\u0641 \u0627\u0644\u0645\u0641\u0642\u0648\u062f\u064a\u0646", "description": "\u0627\u0654\u0641\u0627\u062f\u062a \u0627\u0644\u0633\u0644\u0637\u0627\u062a \u0641\u064a \u0641\u0646\u0632\u0648\u064a\u0644\u0627 \u0628\u0627\u0631\u062a\u0641\u0627\u0639 \u0639\u062f\u062f \u0642\u062a\u0644\u0649 \u0627\u0644\u0632\u0644\u0632\u0627\u0644\u064a\u0646 \u0627\u0644\u0644\u0630\u064a\u0646 \u0636\u0631\u0628\u0627 \u0627\u0644\u0628\u0644\u0627\u062f \u0627\u0655\u0644\u0649 1430 \u0642\u062a\u064a\u0644\u064b\u0627\u060c \u0627\u0655\u0636\u0627\u0641\u0629 \u0627\u0655\u0644\u0649 \u0639\u0634\u0631\u0627\u062a \u0627\u0653\u0644\u0627\u0641 \u0627\u0644\u0645\u0641\u0642\u0648\u062f\u064a\u0646 \u0641\u064a\u0645\u0627 \u0642\u062f\u064e\u0651\u0631\u062a \u0627\u0644\u0627\u0654\u0645\u0645 \u0627\u0644\u0645\u062a\u062d\u062f\u0629 \u062a\u0627\u0654\u062b\u0631 \u0646\u062d\u0648 6.8 \u0645\u0644\u0627\u064a\u064a\u0646 \u0634\u062e\u0635 \u0648\u0641\u0642 \u0627\u0644\u0645\u0646\u0638\u0645\u0629 \u0627\u0644\u062f\u0648\u0644\u064a\u0629 \u0644\u0644\u0647\u062c\u0631\u0629. \u0627\u0654\u0641\u0627\u062f\u062a \u0648\u0643\u0627\u0644\u0629 \"\u0631\u0648\u064a\u062a\u0631\u0632\" \u0645\u0633\u0627\u0621 \u0627\u0644\u0633\u0628\u062a\u060c \u0628\u0627\u0654\u0646 \u0632\u0644\u0632\u0627\u0644\u064b\u0627 \u062c\u062f\u064a\u062f\u064b\u0627 \u0628\u0642\u0648\u0629 5.6 \u062f\u0631\u062c\u0627\u062a \u0636\u0631\u0628 \u0645\u062d\u064a\u0637 \u0645\u0646\u0637\u0642\u0629 \u0627\u0654\u0631\u0627\u062c\u0648\u0627 \u0634\u0645\u0627\u0644\u064a \u0641\u0646\u0632\u0648\u064a\u0644\u0627.", "content": "ONLY AVAILABLE IN PAID PLANS", "keywords": null, "creator": ["\u0641\u064a\u062a\u0648"], "language": "arabic", "country": ["egypt"], "category": ["top", "environment"], "datatype": "news", "pubDate": "2026-06-28 02:09:40", "pubDateTZ": "UTC", "fetched_at": "2026-06-28 02:09:40", "image_url": "https://www.vetogate.com/UploadCache/libfiles/587/5/600x338o/693.webp", "video_url": null, "source_id": "vetogate", "source_name": "\u0641\u064a\u062a\u0648", "source_priority": 59162, "source_url": "https://www.vetogate.com", "source_icon": "https://n.bytvi.com/vetogate.png", "sentiment": "ONLY AVAILABLE IN PROFESSIONAL AND CORPORATE PLANS", "sentiment_stats": "ONLY AVAILABLE IN PROFESSIONAL AND CORPORATE PLANS", "ai_tag": "ONLY AVAILABLE IN PROFESSIONAL AND CORPORATE PLANS", "ai_region": "ONLY AVAILABLE IN CORPORATE PLANS", "ai_org": "ONLY AVAILABLE IN CORPORATE PLANS", "ai_summary": "ONLY AVAILABLE IN PAID PLANS", "duplicate": false}, {"article_id": "ecda07f014c1186e9cd061fa309af701", "link": "https://www.kooora.com/%D9%83%D8%B1%D8%A9-%D9%82%D8%AF%D9%85/%D8%A3%D8%AE%D8%A8%D8%A7%D8%B1/%D8%AA%D8%A7%D9%94%D9%87%D9%84-%D8%AA%D8%A7%D8%B1%D9%8A%D8%AE%D9%8A--%D8%A7%D9%84%D9%83%D9%88%D9%86%D8%BA%D9%88-%D8%AA%D8%B9%D8%A7%D9%82%D8%A8-%D8%A7%D9%94%D9%88%D8%B2%D8%A8%D9%83%D8%B3%D8%AA%D8%A7%D9%86-%D9%88%D8%AA%D8%B5%D8%B7%D8%AF%D9%85-%D8%A8%D8%AE%D8%B5%D9%85-%D8%A7%D9%94%D9%88%D8%B1%D9%88%D8%A8%D9%8A/blt009fc9e38675399b", "title": "Congo DR v Uzbekistan: Group K - FIFA World Cup 2026", "description": "\u0642\u0644\u0628 \u0645\u0646\u062a\u062e\u0628 \u0627\u0644\u0643\u0648\u0646\u063a\u0648 \u0627\u0644\u062f\u064a\u0645\u0642\u0631\u0627\u0637\u064a\u0629\u060c \u062a\u0627\u0654\u062e\u0631\u0647 \u0627\u0654\u0645\u0627\u0645 \u0627\u0654\u0648\u0632\u0628\u0643\u0633\u062a\u0627\u0646\u060c \u0627\u0655\u0644\u0649 \u0641\u0648\u0632 \u062b\u0645\u064a\u0646 \u0628\u0646\u062a\u064a\u062c\u0629 3-1 \u0641\u062c\u0631 \u0627\u0644\u064a\u0648\u0645 \u0627\u0644\u0627\u0654\u062d\u062f\u060c \u0641\u064a \u062e\u062a\u0627\u0645 \u062f\u0648\u0631 \u0627\u0644\u0645\u062c\u0645\u0648\u0639\u0627\u062a \u0644\u0643\u0627\u0654\u0633 \u0627\u0644\u0639\u0627\u0644\u0645 2026.", "content": "ONLY AVAILABLE IN PAID PLANS", "keywords": ["\u0625\u0646\u062c\u0644\u062a\u0631\u0627", "\u064a\u062d\u062f\u062f \u0644\u0627\u062d\u0642\u0627 \u0636\u062f \u064a\u062d\u062f\u062f \u0644\u0627\u062d\u0642\u0627", "\u0627\u0644\u0643\u0648\u0646\u063a\u0648 \u0627\u0644\u062f\u064a\u0645\u0642\u0631\u0627\u0637\u064a\u0629 \u0636\u062f \u0623\u0648\u0632\u0628\u0643\u0633\u062a\u0627\u0646", "\u0643\u0631\u0629 \u0642\u062f\u0645", "\u0627\u0644\u0643\u0648\u0646\u063a\u0648 \u0627\u0644\u062f\u064a\u0645\u0642\u0631\u0627\u0637\u064a\u0629", "\u0623\u0648\u0632\u0628\u0643\u0633\u062a\u0627\u0646", "\u0643\u0623\u0633 \u0627\u0644\u0639\u0627\u0644\u0645"], "creator": ["\u0645\u062d\u0645\u062f \u0645\u0646\u0633\u064a"], "language": "english", "country": ["morocco", "saudi arabia", "tunisia", "egypt", "kuwait", "bahrain", "algeria", "qatar", "jordan", "united arab emirates"], "category": ["sports"], "datatype": "news", "pubDate": "2026-06-28 02:09:08", "pubDateTZ": "UTC", "fetched_at": "2026-06-28 02:31:54", "image_url": "https://assets.kooora.com/images/v3/getty-2283638688/crop/MM5DENZQGQ5DCNJSGE5G433XMU5DKOJVHIZTAMI=/GettyImages-2283638688.jpg?auto=webp&format=jpg&quality=80", "video_url": null, "source_id": "kooora", "source_name": "\u0643\u0648\u0648\u0648\u0631\u0629", "source_priority": 4562, "source_url": "https://www.kooora.com", "source_icon": "https://n.bytvi.com/kooora.jpg", "sentiment": "ONLY AVAILABLE IN PROFESSIONAL AND CORPORATE PLANS", "sentiment_stats": "ONLY AVAILABLE IN PROFESSIONAL AND CORPORATE PLANS", "ai_tag": "ONLY AVAILABLE IN PROFESSIONAL AND CORPORATE PLANS", "ai_region": "ONLY AVAILABLE IN CORPORATE PLANS", "ai_org": "ONLY AVAILABLE IN CORPORATE PLANS", "ai_summary": "ONLY AVAILABLE IN PAID PLANS", "duplicate": true}, {"article_id": "6cc3c6452faf888127a96dbf375ec507", "link": "https://www.vetogate.com/5683022", "title": "\u0627\u0646\u062a\u0634\u0627\u0631 \u0642\u0648\u0627\u062a \u062e\u0627\u0635\u0629 \u062f\u0627\u062e\u0644 \u0627\u0644\u0645\u0646\u0637\u0642\u0629 \u0627\u0644\u062e\u0636\u0631\u0627\u0621 \u0648\u0633\u0637 \u0628\u063a\u062f\u0627\u062f \u0648\u0627\u0654\u0646\u0628\u0627\u0621 \u0639\u0646 \u0627\u0639\u062a\u0642\u0627\u0644 \u0645\u0633\u0648\u0654\u0648\u0644\u064a\u0646 \u0643\u0628\u0627\u0631 (\u0641\u064a\u062f\u064a\u0648)", "description": "\u0642\u0627\u0644 \u0645\u0635\u062f\u0631 \u0627\u0654\u0645\u0646\u064a \u0639\u0631\u0627\u0642\u064a \u0627\u0655\u0646 \u0642\u0648\u0627\u062a \u062e\u0627\u0635\u0629 \u0627\u0646\u062a\u0634\u0631\u062a \u062f\u0627\u062e\u0644 \u0627\u0644\u0645\u0646\u0637\u0642\u0629 \u0627\u0644\u062e\u0636\u0631\u0627\u0621 \u0648\u0633\u0637 \u0627\u0644\u0639\u0627\u0635\u0645\u0629 \u0627\u0644\u0639\u0631\u0627\u0642\u064a\u0629 \u0628\u063a\u062f\u0627\u062f \u062a\u0632\u0627\u0645\u0646\u064b\u0627 \u0645\u0639 \u0627\u0654\u0646\u0628\u0627\u0621 \u0639\u0646 \u062a\u0646\u0641\u064a\u0630 \u0627\u0639\u062a\u0642\u0627\u0644\u0627\u062a \u0637\u0627\u0644\u062a \u0645\u0633\u0648\u0654\u0648\u0644\u064a\u0646 \u0633\u064a\u0627\u0633\u064a\u064a\u0646 \u0643\u0628\u0627\u0631\u064b\u0627 \u0648\u0639\u0646\u0627\u0635\u0631 \u062d\u0645\u0627\u064a\u0629 \u0645\u062a\u0648\u0631\u0637\u0629 \u0628\u0645\u0644\u0641\u0627\u062a \u0641\u0633\u0627\u062f. \u0648\u0627\u0654\u0636\u0627\u0641 \u0627\u0644\u0645\u0635\u062f\u0631 \u0644\u0648\u0643\u0627\u0644\u0629 \"\u0634\u0641\u0642 \u0646\u064a\u0648\u0632\" \u0627\u0654\u0646 \u0642\u0648\u0627\u062a \u062e\u0627\u0635\u0629 \u0627\u0646\u062a\u0634\u0631\u062a \u0641\u064a \u0645\u062d\u064a\u0637 \u0639\u062f\u062f \u0645\u0646 \u0627\u0644\u0645\u0642\u0631\u0627\u062a \u0627\u0644\u062d\u0633\u0627\u0633\u0629 \u062f\u0627\u062e\u0644 \u0627\u0644\u0645\u0646\u0637\u0642\u0629 \u0627\u0644\u062e\u0636\u0631\u0627\u0621 \u0645\u0639 \u062a\u0634\u062f\u064a\u062f \u0627\u0644\u0627\u0655\u062c\u0631\u0627\u0621\u0627\u062a", "content": "ONLY AVAILABLE IN PAID PLANS", "keywords": null, "creator": ["\u0641\u064a\u062a\u0648"], "language": "arabic", "country": ["egypt"], "category": ["top", "crime"], "datatype": "news", "pubDate": "2026-06-28 02:08:47", "pubDateTZ": "UTC", "fetched_at": "2026-06-28 02:08:47", "image_url": "https://www.vetogate.com/UploadCache/libfiles/587/5/600x338o/695.webp", "video_url": null, "source_id": "vetogate", "source_name": "\u0641\u064a\u062a\u0648", "source_priority": 59162, "source_url": "https://www.vetogate.com", "source_icon": "https://n.bytvi.com/vetogate.png", "sentiment": "ONLY AVAILABLE IN PROFESSIONAL AND CORPORATE PLANS", "sentiment_stats": "ONLY AVAILABLE IN PROFESSIONAL AND CORPORATE PLANS", "ai_tag": "ONLY AVAILABLE IN PROFESSIONAL AND CORPORATE PLANS", "ai_region": "ONLY AVAILABLE IN CORPORATE PLANS", "ai_org": "ONLY AVAILABLE IN CORPORATE PLANS", "ai_summary": "ONLY AVAILABLE IN PAID PLANS", "duplicate": false}, {"article_id": "2f6ac4324a6421f2343968617e752d4c", "link": "https://menafn.com/1111321981/Syria-Sends-First-Ever-Overseas-Rescue-Team-Aids-to-Venezuela", "title": "Syria Sends First-Ever Overseas Rescue Team, Aids to Venezuela", "description": "(MENAFN) Syria dispatched a rescue team to Venezuela on Saturday to join search-and-rescue efforts following devastating earthquakes earlier in the week \u2013 marking the first time Syrian rescue ...", "content": "ONLY AVAILABLE IN PAID PLANS", "keywords": null, "creator": null, "language": "english", "country": ["qatar", "kuwait", "yemen", "egypt", "syria", "lebanon", "morocco", "libya", "bahrain", "united arab emirates", "algeria", "tunisia", "iraq", "saudi arabia", "jordan"], "category": ["top", "environment"], "datatype": "news", "pubDate": "2026-06-28 02:08:28", "pubDateTZ": "UTC", "fetched_at": "2026-06-28 07:35:33", "image_url": null, "video_url": null, "source_id": "menafn", "source_name": "Menafn", "source_priority": 28392, "source_url": "https://menafn.com", "source_icon": "https://n.bytvi.com/menafn.png", "sentiment": "ONLY AVAILABLE IN PROFESSIONAL AND CORPORATE PLANS", "sentiment_stats": "ONLY AVAILABLE IN PROFESSIONAL AND CORPORATE PLANS", "ai_tag": "ONLY AVAILABLE IN PROFESSIONAL AND CORPORATE PLANS", "ai_region": "ONLY AVAILABLE IN CORPORATE PLANS", "ai_org": "ONLY AVAILABLE IN CORPORATE PLANS", "ai_summary": "ONLY AVAILABLE IN PAID PLANS", "duplicate": false}, {"article_id": "1655bb02991e4f577d5da14b2e2cf674", "link": "https://www.vetogate.com/5683026", "title": "\u0627\u0644\u0628\u062d\u0631\u064a\u0629 \u0627\u0644\u0627\u0655\u064a\u0631\u0627\u0646\u064a\u0629: \u0627\u0644\u0642\u0648\u0627\u0639\u062f \u0627\u0644\u0627\u0654\u0645\u0631\u064a\u0643\u064a\u0629 \u0641\u064a \u0627\u0644\u0645\u0646\u0637\u0642\u0629 \u0644\u0647\u0627 \u0631\u0648\u0627\u064a\u0629 \u0645\u062e\u062a\u0644\u0641\u0629 \u0648\u0633\u062a\u0648\u0627\u062c\u0647 \u062c\u062d\u064a\u0645\u0627 \u0647\u0630\u0647 \u0627\u0644\u0627\u0654\u064a\u0627\u0645", "description": "\u0627\u0654\u0639\u0644\u0646 \u0627\u0644\u062d\u0631\u0633 \u0627\u0644\u062b\u0648\u0631\u064a \u0627\u0644\u0627\u0655\u064a\u0631\u0627\u0646\u064a\u060c \u0641\u062c\u0631 \u0627\u0644\u0627\u0654\u062d\u062f\u060c \u0641\u064a \u0628\u064a\u0627\u0646\u060c \u0627\u0654\u0646\u0651 \u0627\u0644\u0642\u0648\u0627\u062a \u0627\u0644\u0628\u062d\u0631\u064a\u0629 \u0648\u0627\u0644\u062c\u0648 \u0641\u0636\u0627\u064a\u0654\u064a\u0629 \u0646\u0641\u0651\u0630\u062a\u0627\u060c \u0628\u064a\u0646 \u0627\u0644\u0633\u0627\u0639\u0629 \u0627\u0644\u062b\u0627\u0646\u064a\u0629 \u0648\u0627\u0644\u062b\u0627\u0644\u062b\u0629 \u0641\u062c\u0631 \u0627\u0644\u064a\u0648\u0645 \u0627\u0644\u0627\u0654\u062d\u062f\u060c \u0639\u0645\u0644\u064a\u0629 \u0645\u0634\u062a\u0631\u0643\u0629 \u0628\u0627\u0644\u0635\u0648\u0627\u0631\u064a\u062e \u0648\u0627\u0644\u0637\u0627\u064a\u0654\u0631\u0627\u062a \u0627\u0644\u0645\u0633\u064a\u0631\u0629 \u0627\u0633\u062a\u0647\u062f\u0641\u062a 8 \u0645\u0648\u0627\u0642\u0639 \u0639\u0633\u0643\u0631\u064a\u0629 \u0645\u0647\u0645\u0629 \u062a\u0627\u0628\u0639\u0629 \u0644\u062c\u064a\u0634 \u0627\u0644\u0648\u0644\u0627\u064a\u0627\u062a \u0627\u0644\u0645\u062a\u062d\u062f\u0629. \u0648\u0627\u0654\u0648\u0636\u062d \u0627\u0644\u0628\u064a\u0627\u0646 \u0627\u0654\u0646\u0651 \u0627\u0644\u0639\u0645\u0644\u064a\u0629 \u0637\u0627\u0644\u062a \u0642\u0627\u0639\u062f\u0629 \u0639\u0644\u064a \u0627\u0644\u0633\u0627\u0644\u0645 \u0641\u064a \u0627\u0644\u0643\u0648\u064a\u062a\u060c \u0627\u0655\u0636\u0627\u0641\u0629 \u0627\u0655\u0644\u0649 \u0645\u0642\u0631", "content": "ONLY AVAILABLE IN PAID PLANS", "keywords": null, "creator": ["\u0641\u064a\u062a\u0648"], "language": "arabic", "country": ["egypt"], "category": ["top", "crime", "politics"], "datatype": "news", "pubDate": "2026-06-28 02:08:05", "pubDateTZ": "UTC", "fetched_at": "2026-06-28 02:08:05", "image_url": "https://www.vetogate.com/UploadCache/libfiles/587/5/600x338o/697.webp", "video_url": null, "source_id": "vetogate", "source_name": "\u0641\u064a\u062a\u0648", "source_priority": 59162, "source_url": "https://www.vetogate.com", "source_icon": "https://n.bytvi.com/vetogate.png", "sentiment": "ONLY AVAILABLE IN PROFESSIONAL AND CORPORATE PLANS", "sentiment_stats": "ONLY AVAILABLE IN PROFESSIONAL AND CORPORATE PLANS", "ai_tag": "ONLY AVAILABLE IN PROFESSIONAL AND CORPORATE PLANS", "ai_region": "ONLY AVAILABLE IN CORPORATE PLANS", "ai_org": "ONLY AVAILABLE IN CORPORATE PLANS", "ai_summary": "ONLY AVAILABLE IN PAID PLANS", "duplicate": false}, {"article_id": "c73d37b0e08148a3ace455948a084087", "link": "https://menafn.com/1111321978/US-President-Announces-Airstrikes-On-Iranian-Targets-Threatens-Military-Escalation-If-Ceasefire-Is-Violated", "title": "US President Announces Airstrikes On Iranian Targets, Threatens Military Escalation If Ceasefire Is Violated #President #Announces #Airstrikes #Iranian #Targets, #Threatens #Military #Escalation #Ceasefire #Violated #Apple #Samsung #Google #AI #Chat #GPT #Cyber #Security", "description": "(MENAFN - Gulf Times) US President Donald Trump announced that US aircraft struck Iranian missile and drone storage locations and coastal radar sites \"for violating the Cease Fire Agreement.\"In a ...", "content": "ONLY AVAILABLE IN PAID PLANS", "keywords": null, "creator": null, "language": "english", "country": ["saudi arabia", "united arab emirates", "morocco", "jordan", "iraq", "bahrain", "kuwait", "qatar", "egypt", "lebanon"], "category": ["top", "crime", "politics"], "datatype": "news", "pubDate": "2026-06-28 02:08:01", "pubDateTZ": "UTC", "fetched_at": "2026-06-28 13:35:34", "image_url": "https://menafn.com/updates/PR/2026-06/28/GT_64a8aimage_story_social.jpg", "video_url": null, "source_id": "menafn", "source_name": "Menafn", "source_priority": 28392, "source_url": "https://menafn.com", "source_icon": "https://n.bytvi.com/menafn.png", "sentiment": "ONLY AVAILABLE IN PROFESSIONAL AND CORPORATE PLANS", "sentiment_stats": "ONLY AVAILABLE IN PROFESSIONAL AND CORPORATE PLANS", "ai_tag": "ONLY AVAILABLE IN PROFESSIONAL AND CORPORATE PLANS", "ai_region": "ONLY AVAILABLE IN CORPORATE PLANS", "ai_org": "ONLY AVAILABLE IN CORPORATE PLANS", "ai_summary": "ONLY AVAILABLE IN PAID PLANS", "duplicate": false}], "nextPage": "1782612481631561865"}